adax_local/__init__.py
adax_local-0.3.0.dist-info/licenses/LICENSE
adax_local-0.3.0.dist-info/METADATA
adax_local-0.3.0.dist-info/WHEEL
adax_local-0.3.0.dist-info/top_level.txt
adax_local-0.3.0.dist-info/RECORD
