Metadata-Version: 2.4
Name: Adax-local
Version: 0.3.0
Summary: A python3 library to communicate with Adax
Home-page: https://github.com/Danielhiversen/pyAdaxLocal
Author: Daniel Hjelseth Høyer
Author-email: mail@dahoiv.net
License: MIT
Classifier: Intended Audience :: Developers
Classifier: Operating System :: OS Independent
Classifier: Programming Language :: Python
Classifier: Programming Language :: Python :: 3
Classifier: Topic :: Software Development :: Libraries :: Python Modules
Requires-Python: >=3.10.0
License-File: LICENSE
Requires-Dist: aiohttp>=3.0.6
Requires-Dist: async_timeout>=1.4.0
Requires-Dist: bleak
Requires-Dist: bleak-retry-connector>=4.0.0
Dynamic: author
Dynamic: author-email
Dynamic: classifier
Dynamic: home-page
Dynamic: license
Dynamic: license-file
Dynamic: requires-dist
Dynamic: requires-python
Dynamic: summary
